datachain/__init__.py
datachain/__main__.py
datachain/_version.py
datachain/asyn.py
datachain/cache.py
datachain/cli.py
datachain/cli_utils.py
datachain/config.py
datachain/dataset.py
datachain/error.py
datachain/listing.py
datachain/node.py
datachain/nodes_fetcher.py
datachain/nodes_thread_pool.py
datachain/progress.py
datachain/py.typed
datachain/storage.py
datachain/utils.py
datachain/catalog/__init__.py
datachain/catalog/catalog.py
datachain/catalog/datasource.py
datachain/catalog/loader.py
datachain/catalog/subclass.py
datachain/client/__init__.py
datachain/client/azure.py
datachain/client/fileslice.py
datachain/client/fsspec.py
datachain/client/gcs.py
datachain/client/local.py
datachain/client/s3.py
datachain/data_storage/__init__.py
datachain/data_storage/db_engine.py
datachain/data_storage/id_generator.py
datachain/data_storage/job.py
datachain/data_storage/metastore.py
datachain/data_storage/schema.py
datachain/data_storage/serializer.py
datachain/data_storage/sqlite.py
datachain/data_storage/warehouse.py
datachain/lib/__init__.py
datachain/lib/cached_stream.py
datachain/lib/claude.py
datachain/lib/dc.py
datachain/lib/feature.py
datachain/lib/feature_registry.py
datachain/lib/feature_utils.py
datachain/lib/file.py
datachain/lib/gpt4_vision.py
datachain/lib/hf_image_to_text.py
datachain/lib/hf_pipeline.py
datachain/lib/image.py
datachain/lib/image_transform.py
datachain/lib/iptc_exif_xmp.py
datachain/lib/parquet.py
datachain/lib/pytorch.py
datachain/lib/reader.py
datachain/lib/settings.py
datachain/lib/signal_schema.py
datachain/lib/text.py
datachain/lib/udf.py
datachain/lib/udf_signature.py
datachain/lib/unstructured.py
datachain/lib/utils.py
datachain/lib/vfile.py
datachain/lib/webdataset.py
datachain/lib/webdataset_laion.py
datachain/query/__init__.py
datachain/query/batch.py
datachain/query/builtins.py
datachain/query/dataset.py
datachain/query/dispatch.py
datachain/query/params.py
datachain/query/schema.py
datachain/query/session.py
dvcx-0.95.0.dist-info/LICENSE
dvcx-0.95.0.dist-info/METADATA
dvcx-0.95.0.dist-info/WHEEL
dvcx-0.95.0.dist-info/entry_points.txt
dvcx-0.95.0.dist-info/top_level.txt
dvcx-0.95.0.dist-info/RECORD
