Metadata-Version: 2.1
Name: dvcx
Version: 0.95.0
Summary: DVCx
Author-email: Dmitry Petrov <support@dvc.org>
License: Apache-2.0
Project-URL: Issues, https://github.com/iterative/dvcx/issues
Project-URL: Source, https://github.com/iterative/dvcx
Classifier: Programming Language :: Python :: 3
Classifier: Programming Language :: Python :: 3.9
Classifier: Programming Language :: Python :: 3.10
Classifier: Programming Language :: Python :: 3.11
Classifier: Programming Language :: Python :: 3.12
Classifier: Development Status :: 2 - Pre-Alpha
Requires-Python: >=3.9
License-File: LICENSE
Requires-Dist: pyyaml
Requires-Dist: tomlkit
Requires-Dist: tqdm
Requires-Dist: numpy
Requires-Dist: pandas >=2.0.0
Requires-Dist: pyarrow
Requires-Dist: typing-extensions
Requires-Dist: python-dateutil >=2
Requires-Dist: attrs >=21.3.0
Requires-Dist: s3fs >=2024.2.0
Requires-Dist: gcsfs >=2024.2.0
Requires-Dist: adlfs >=2024.2.0
Requires-Dist: dvc-data <4,>=3.10
Requires-Dist: dvc-objects <6,>=4
Requires-Dist: shtab <2,>=1.3.4
Requires-Dist: sqlalchemy >=2
Requires-Dist: multiprocess ==0.70.16
Requires-Dist: dill ==0.3.8
Requires-Dist: ujson >=5.9.0
Requires-Dist: pydantic <3,>=2
Requires-Dist: numpy <2,>=1 ; sys_platform == "win32"
Provides-Extra: cv
Requires-Dist: Pillow <11,>=10.0.0 ; extra == 'cv'
Requires-Dist: torch >=2.1.0 ; extra == 'cv'
Requires-Dist: torchvision ; extra == 'cv'
Requires-Dist: transformers >=4.36.0 ; extra == 'cv'
Provides-Extra: dev
Requires-Dist: dvcx[tests] ; extra == 'dev'
Requires-Dist: mypy ==1.10.0 ; extra == 'dev'
Requires-Dist: types-python-dateutil ; extra == 'dev'
Requires-Dist: types-PyYAML ; extra == 'dev'
Requires-Dist: types-requests ; extra == 'dev'
Requires-Dist: types-ujson ; extra == 'dev'
Provides-Extra: remote
Requires-Dist: dvcx[pandas] ; extra == 'remote'
Requires-Dist: lz4 ; extra == 'remote'
Requires-Dist: msgpack <2,>=1.0.4 ; extra == 'remote'
Requires-Dist: requests >=2.22.0 ; extra == 'remote'
Provides-Extra: tests
Requires-Dist: dvcx[cv,pandas,remote,vector] ; extra == 'tests'
Requires-Dist: pytest <9,>=8 ; extra == 'tests'
Requires-Dist: pytest-sugar >=0.9.6 ; extra == 'tests'
Requires-Dist: pytest-cov >=4.1.0 ; extra == 'tests'
Requires-Dist: pytest-mock >=3.12.0 ; extra == 'tests'
Requires-Dist: pytest-servers[all] >=0.5.4 ; extra == 'tests'
Requires-Dist: pytest-benchmark[histogram] ; extra == 'tests'
Requires-Dist: pytest-asyncio >=0.23.2 ; extra == 'tests'
Requires-Dist: pytest-xdist >=3.3.1 ; extra == 'tests'
Requires-Dist: virtualenv ; extra == 'tests'
Requires-Dist: dulwich ; extra == 'tests'
Requires-Dist: hypothesis ; extra == 'tests'
Requires-Dist: open-clip-torch ; extra == 'tests'
Requires-Dist: aiotools >=1.7.0 ; extra == 'tests'
Requires-Dist: requests-mock ; extra == 'tests'
Provides-Extra: vector
Requires-Dist: scipy ; extra == 'vector'
